aws_key_rotator/__init__.py
aws_key_rotator/cli.py
aws_key_rotator/constants.py
aws_key_rotator/rotator.py
aws_key_rotator-0.1.2.dist-info/entry_points.txt
aws_key_rotator-0.1.2.dist-info/LICENSE.md
aws_key_rotator-0.1.2.dist-info/WHEEL
aws_key_rotator-0.1.2.dist-info/METADATA
aws_key_rotator-0.1.2.dist-info/RECORD
